checkpea/__init__.py
checkpea-0.1.1.dist-info/WHEEL
checkpea-0.1.1.dist-info/METADATA
checkpea-0.1.1.dist-info/RECORD
