Metadata-Version: 2.1
Name: checkpea
Version: 0.1.1
Summary: Checkpea tracks the state of your application.
Author: Dani Perez
Author-email: daniel.perez@example.com
Requires-Python: >=3.7,<4.0
Classifier: Programming Language :: Python :: 3
Classifier: Programming Language :: Python :: 3.7
Classifier: Programming Language :: Python :: 3.8
Classifier: Programming Language :: Python :: 3.9
